threatmodel/__init__.py
threatmodel/asset.py
threatmodel/component.py
threatmodel/data_flow.py
threatmodel/diagram.py
threatmodel/element.py
threatmodel/mitigation.py
threatmodel/model.py
threatmodel/node.py
threatmodel/otm.py
threatmodel/plus/__init__.py
threatmodel/plus/browser.py
threatmodel/plus_aws/__init__.py
threatmodel/plus_aws/application_load_balancer.py
threatmodel/score.py
threatmodel/table_format.py
threatmodel/tag.py
threatmodel/threat.py
threatmodel/threatlib/__init__.py
threatmodel/trust_boundary.py
threatmodel-0.0.19.dist-info/LICENSE
threatmodel-0.0.19.dist-info/WHEEL
threatmodel-0.0.19.dist-info/METADATA
threatmodel-0.0.19.dist-info/RECORD
