Metadata-Version: 2.1
Name: threatmodel
Version: 0.0.19
Summary: Agile Threat Modeling as Code
Home-page: https://github.com/hupe1980/threatmodel
License: MIT
Keywords: agile,threat-modeling,cybersecurity,appsec,threatbook,jupyter-notebook,OpenThreatModel,otm
Author: hupe1980
Requires-Python: >=3.11,<4.0
Classifier: License :: OSI Approved :: MIT License
Classifier: Programming Language :: Python
Classifier: Programming Language :: Python :: 3
Classifier: Programming Language :: Python :: 3.11
Classifier: Programming Language :: Python :: 3
Classifier: Topic :: Security
Requires-Dist: graphviz (>=0.20.1,<0.21.0)
Requires-Dist: tabulate (>=0.9.0,<0.10.0)
Project-URL: Repository, https://github.com/hupe1980/threatmodel
